watchtower_logging/__init__.py
watchtower_logging/exceptions.py
watchtower_logging/watchtower_logging.py
watchtower_logging/watchtower_handler/__init__.py
watchtower_logging-0.1.0.dist-info/METADATA
watchtower_logging-0.1.0.dist-info/WHEEL
watchtower_logging-0.1.0.dist-info/top_level.txt
watchtower_logging-0.1.0.dist-info/RECORD
